datasette_sqlite_xl/__init__.py
datasette_sqlite_xl-0.0.1a4.dist-info/METADATA
datasette_sqlite_xl-0.0.1a4.dist-info/WHEEL
datasette_sqlite_xl-0.0.1a4.dist-info/entry_points.txt
datasette_sqlite_xl-0.0.1a4.dist-info/top_level.txt
datasette_sqlite_xl-0.0.1a4.dist-info/RECORD
