Metadata-Version: 2.1
Name: datasette-sqlite-xl
Version: 0.0.1a4
Home-page: https://TODO.com
Author: TODO
License: MIT License, Apache License, Version 2.0
Requires-Dist: datasette
Requires-Dist: sqlite-xl (==0.0.1-alpha.4)
